tsne/bh_sne.cpython-35m-x86_64-linux-gnu.so
tsne/bh_sne_3d.cpython-35m-x86_64-linux-gnu.so
tsne/_version.py
tsne/__init__.py
tsne/.libs/libgomp-3300acd3.so.1.0.0
tests/test_iris.py
tests/test_seed.py
tests/__init__.py
tsne_mp-0.1.13.data/scripts/bhtsne.py
tsne_mp-0.1.13.dist-info/RECORD
tsne_mp-0.1.13.dist-info/METADATA
tsne_mp-0.1.13.dist-info/WHEEL
tsne_mp-0.1.13.dist-info/top_level.txt
