Metadata-Version: 2.1
Name: tsne-mp
Version: 0.1.13
Summary: High Performance TSNE implementations for python
Home-page: https://github.com/rappdw/tsne.git
Author: Daniel Rapp
Author-email: rappdw@gmail.com
License: Apache License Version 2.0, January 2004
Platform: UNKNOWN
Classifier: Development Status :: 5 - Production/Stable
Classifier: Intended Audience :: Developers
Classifier: Topic :: Scientific/Engineering :: Visualization
Classifier: Topic :: Software Development :: Libraries :: Python Modules
Classifier: License :: OSI Approved :: Apache Software License
Classifier: Programming Language :: Python :: 3.5
Classifier: Programming Language :: Python :: 3.6
Classifier: Programming Language :: Python :: 3.7
Requires-Dist: numpy
Requires-Dist: scipy
